what2_grapheme-0.5.2.dist-info/METADATA
what2_grapheme-0.5.2.dist-info/WHEEL
what2_grapheme-0.5.2.dist-info/entry_points.txt
what2_grapheme-0.5.2.dist-info/licenses/LICENSE.md
what2_grapheme/__init__.py
what2_grapheme/api.py
what2_grapheme/fast_re/__init__.py
what2_grapheme/fast_re/api.py
what2_grapheme/fast_re/internal.py
what2_grapheme/grapheme_data/__init__.py
what2_grapheme/grapheme_data/data/DerivedCoreProperties.txt
what2_grapheme/grapheme_data/data/GraphemeBreakProperty.txt
what2_grapheme/grapheme_data/data/README.md
what2_grapheme/grapheme_data/data/__init__.py
what2_grapheme/grapheme_data/data/emoji-data.txt
what2_grapheme/grapheme_data/data/license.txt
what2_grapheme/grapheme_data/load.py
what2_grapheme/grapheme_property/__init__.py
what2_grapheme/grapheme_property/cache.py
what2_grapheme/grapheme_property/file_reader.py
what2_grapheme/grapheme_property/lookup.py
what2_grapheme/grapheme_property/type.py
what2_grapheme/py.typed
what2_grapheme/util/__init__.py
what2_grapheme/util/caching.py
what2_grapheme/util/iter.py
what2_grapheme-0.5.2.dist-info/RECORD
