Metadata-Version: 2.1
Name: what2-grapheme
Version: 0.5.2
Summary: A pure Python implementation of the Unicode algorithm for breaking strings of text into extended grapheme clusters ("user-perceived characters").
Author-Email: Marc Edwards <marc@mlwhat.com>
License: MIT
Project-URL: Repository, https://github.com/alwaysmpe/what2_grapheme
Requires-Python: >=3.13
Requires-Dist: what2-regex>=0.1.0
